{"nodes": [{"id": "src_app_contact_page_tsx", "label": "page.tsx", "file_type": "code", "source_file": "src/app/contact/page.tsx", "source_location": "L1"}, {"id": "page_useist", "label": "useIST()", "file_type": "code", "source_file": "src/app/contact/page.tsx", "source_location": "L11"}, {"id": "page_handlechange", "label": "handleChange()", "file_type": "code", "source_file": "src/app/contact/page.tsx", "source_location": "L67"}, {"id": "page_handlecompanychange", "label": "handleCompanyChange()", "file_type": "code", "source_file": "src/app/contact/page.tsx", "source_location": "L74"}, {"id": "page_handlesubmit", "label": "handleSubmit()", "file_type": "code", "source_file": "src/app/contact/page.tsx", "source_location": "L81"}, {"id": "page_handlecompanysubmit", "label": "handleCompanySubmit()", "file_type": "code", "source_file": "src/app/contact/page.tsx", "source_location": "L116"}], "edges": [{"source": "src_app_contact_page_tsx", "target": "react", "relation": "imports_from", "confidence": "EXTRACTED", "source_file": "src/app/contact/page.tsx", "source_location": "L3", "weight": 1.0}, {"source": "src_app_contact_page_tsx", "target": "link", "relation": "imports_from", "confidence": "EXTRACTED", "source_file": "src/app/contact/page.tsx", "source_location": "L4", "weight": 1.0}, {"source": "src_app_contact_page_tsx", "target": "src_app_contact_theme", "relation": "imports_from", "confidence": "EXTRACTED", "source_file": "src/app/contact/page.tsx", "source_location": "L5", "weight": 1.0}, {"source": "src_app_contact_page_tsx", "target": "src_app_contact_components_navbar", "relation": "imports_from", "confidence": "EXTRACTED", "source_file": "src/app/contact/page.tsx", "source_location": "L6", "weight": 1.0}, {"source": "src_app_contact_page_tsx", "target": "page_useist", "relation": "contains", "confidence": "EXTRACTED", "source_file": "src/app/contact/page.tsx", "source_location": "L11", "weight": 1.0}, {"source": "src_app_contact_page_tsx", "target": "page_handlechange", "relation": "contains", "confidence": "EXTRACTED", "source_file": "src/app/contact/page.tsx", "source_location": "L67", "weight": 1.0}, {"source": "src_app_contact_page_tsx", "target": "page_handlecompanychange", "relation": "contains", "confidence": "EXTRACTED", "source_file": "src/app/contact/page.tsx", "source_location": "L74", "weight": 1.0}, {"source": "src_app_contact_page_tsx", "target": "page_handlesubmit", "relation": "contains", "confidence": "EXTRACTED", "source_file": "src/app/contact/page.tsx", "source_location": "L81", "weight": 1.0}, {"source": "src_app_contact_page_tsx", "target": "page_handlecompanysubmit", "relation": "contains", "confidence": "EXTRACTED", "source_file": "src/app/contact/page.tsx", "source_location": "L116", "weight": 1.0}]}